{"page": 2, "results": [{"adult": false, "backdrop_path": "/2spY2G6LpRaF798DdQ7ITBY1nMc.jpg", "genre_ids": [18, 9648, 53], "id": 1153302, "original_language": "en", "original_title": "Three", "overview": "", "popularity": 21.874, "poster_path": "/AbpeOoj2T5fvuihxbvK2lNnTJFT.jpg", "release_date": "2023-07-29", "title": "Three", "video": false, "vote_average": 0, "vote_count": 0}, {"adult": false, "backdrop_path": null, "genre_ids": [10751], "id": 974834, "original_language": "en", "original_title": "American Girl: Corinne Tan", "overview": "", "popularity": 2.206, "poster_path": "/fUjqTWKzzbBL2BrRRE4J5qw8t8v.jpg", "release_date": "2023-07-28", "title": "American Girl: Corinne Tan", "video": false, "vote_average": 0, "vote_count": 0}, {"adult": false, "backdrop_path": "/2WstGSRtIRyI86oPaMk9FKQZQdw.jpg", "genre_ids": [27], "id": 973471, "original_language": "en", "original_title": "The Sacrifice Game", "overview": "", "popularity": 15.443, "poster_path": "/wTdGv9rdVbERPjTW3TZYrdMyodv.jpg", "release_date": "2023-07-28", "title": "The Sacrifice Game", "video": false, "vote_average": 0, "vote_count": 0}, {"adult": false, "backdrop_path": null, "genre_ids": [], "id": 1153339, "original_language": "en", "original_title": "You're OUT!", "overview": "", "popularity": 14.73, "poster_path": "/qobC0UKf01HUy6M4n5TzImLyovu.jpg", "release_date": "2023-07-28", "title": "You're OUT!", "video": false, "vote_average": 0, "vote_count": 0}, {"adult": false, "backdrop_path": null, "genre_ids": [99], "id": 1153417, "original_language": "en", "original_title": "How Are You Travelling?", "overview": "", "popularity": 23.598, "poster_path": null, "release_date": "2023-07-29", "title": "How Are You Travelling?", "video": false, "vote_average": 0, "vote_count": 0}, {"adult": false, "backdrop_path": null, "genre_ids": [99], "id": 1153420, "original_language": "en", "original_title": "The Last Two Weeks at Longlee", "overview": "", "popularity": 23.451, "poster_path": null, "release_date": "2023-07-29", "title": "The Last Two Weeks at Longlee", "video": false, "vote_average": 0, "vote_count": 0}, {"adult": false, "backdrop_path": null, "genre_ids": [99], "id": 1153422, "original_language": "en", "original_title": "The Burnt Half", "overview": "", "popularity": 23.098, "poster_path": null, "release_date": "2023-07-29", "title": "The Burnt Half", "video": false, "vote_average": 0, "vote_count": 0}, {"adult": false, "backdrop_path": null, "genre_ids": [18], "id": 1150000, "original_language": "en", "original_title": "Daughter of God", "overview": "", "popularity": 15.851, "poster_path": null, "release_date": "2023-07-28", "title": "Daughter of God", "video": false, "vote_average": 0, "vote_count": 0}, {"adult": false, "backdrop_path": null, "genre_ids": [35], "id": 1150005, "original_language": "en", "original_title": "Hey Brainy Man", "overview": "", "popularity": 13.039, "poster_path": null, "release_date": "2023-07-28", "title": "Hey Brainy Man", "video": false, "vote_average": 0, "vote_count": 0}, {"adult": false, "backdrop_path": null, "genre_ids": [16, 10402], "id": 1150037, "original_language": "en", "original_title": "Miles Davis – What's Love Got to Do with It", "overview": "", "popularity": 13.241, "poster_path": null, "release_date": "2023-07-28", "title": "Miles Davis – What's Love Got to Do with It", "video": false, "vote_average": 0, "vote_count": 0}, {"adult": false, "backdrop_path": null, "genre_ids": [16], "id": 1150040, "original_language": "en", "original_title": "Aleph", "overview": "", "popularity": 13.17, "poster_path": null, "release_date": "2023-07-28", "title": "Aleph", "video": false, "vote_average": 0, "vote_count": 0}, {"adult": false, "backdrop_path": null, "genre_ids": [], "id": 1150046, "original_language": "en", "original_title": "Cetology", "overview": "", "popularity": 13.17, "poster_path": null, "release_date": "2023-07-28", "title": "Cetology", "video": false, "vote_average": 0, "vote_count": 0}, {"adult": false, "backdrop_path": null, "genre_ids": [18, 35], "id": 1150047, "original_language": "en", "original_title": "Maunga Cassino", "overview": "", "popularity": 13.315, "poster_path": null, "release_date": "2023-07-28", "title": "Maunga Cassino", "video": false, "vote_average": 0, "vote_count": 0}, {"adult": false, "backdrop_path": null, "genre_ids": [27, 35], "id": 1153522, "original_language": "en", "original_title": "Hellmark", "overview": "", "popularity": 21.75, "poster_path": "/tSKMFGXEky0VVZrI1Tzl2XalCfE.jpg", "release_date": "2023-07-29", "title": "Hellmark", "video": false, "vote_average": 0, "vote_count": 0}, {"adult": false, "backdrop_path": null, "genre_ids": [27, 14], "id": 1153536, "original_language": "en", "original_title": "Saint-Sacrifice", "overview": "", "popularity": 16.361, "poster_path": "/sb39uEXLaGFxJvBNyYuCqK1Y25x.jpg", "release_date": "2023-07-28", "title": "Saint-Sacrifice", "video": false, "vote_average": 0, "vote_count": 0}, {"adult": false, "backdrop_path": null, "genre_ids": [16], "id": 1150560, "original_language": "en", "original_title": "The Poultry Punisher", "overview": "", "popularity": 16.604, "poster_path": null, "release_date": "2023-07-28", "title": "The Poultry Punisher", "video": false, "vote_average": 0, "vote_count": 0}, {"adult": false, "backdrop_path": "/7aYW6qmMdN7I6f5i9NoesXpoTfz.jpg", "genre_ids": [99], "id": 1150886, "original_language": "en", "original_title": "Ser vistos", "overview": "", "popularity": 27.161, "poster_path": "/5NeOBWoIqAqAC94swWaCYDTGQOG.jpg", "release_date": "2023-07-29", "title": "Ser vistos", "video": false, "vote_average": 0, "vote_count": 0}, {"adult": false, "backdrop_path": null, "genre_ids": [], "id": 1151073, "original_language": "en", "original_title": "Necessity: Transgender Kiss", "overview": "", "popularity": 12.493, "poster_path": "/hwkmqzt7QT1bJXYYS9OO54dkDD.jpg", "release_date": "2023-07-28", "title": "Necessity: Transgender Kiss", "video": false, "vote_average": 0, "vote_count": 0}, {"adult": false, "backdrop_path": "/tlkSFAvnpkFUc3SUbjBdkUDGHz5.jpg", "genre_ids": [35], "id": 1151086, "original_language": "en", "original_title": "48:00", "overview": "", "popularity": 22.511, "poster_path": "/x8AP3veokP9OxK8NW5QTljjyEaJ.jpg", "release_date": "2023-07-29", "title": "48:00", "video": false, "vote_average": 0, "vote_count": 0}, {"adult": false, "backdrop_path": null, "genre_ids": [18], "id": 1150109, "original_language": "en", "original_title": "Bringing Mere Home", "overview": "", "popularity": 13.352, "poster_path": null, "release_date": "2023-07-28", "title": "Bringing Mere Home", "video": false, "vote_average": 0, "vote_count": 0}], "total_pages": 4, "total_results": 64}